pythonreader/__init__.py
pythonreader/pyreader.py
pyreader-0.0.1.dist-info/LICENSE
pyreader-0.0.1.dist-info/METADATA
pyreader-0.0.1.dist-info/WHEEL
pyreader-0.0.1.dist-info/top_level.txt
pyreader-0.0.1.dist-info/RECORD
